owl/__init__.py
owl/tools.py
owl/cloud/__init__.py
owl/cloud/aws/__init__.py
owl/cloud/aws/common.py
owl/cloud/aws/dynamodb.py
owl/cloud/aws/s3.py
owl/data/__init__.py
owl/data/common.py
owl/data/mongo_manager.py
owl/data/tests/__init__.py
owl/data/tests/test_common.py
owl/data/tests/test_img_tools.py
owl/data/tests/test_mongod.py
owl/database/__init__.py
owl/database/mongo.py
owl/marketing/__init__.py
owl/marketing/mailchimp.py
owl/marketing/email/__init__.py
owl/marketing/email/mailgun.py
owl/marketing/email/sendgrid.py
owl/services/__init__.py
owl/services/webapi.py
owl/third/__init__.py
owl/third/aws/__init__.py
owl/third/aws/common.py
owl/third/aws/dynamodb.py
owl/third/aws/s3.py
projectowl-0.3.20.dist-info/METADATA
projectowl-0.3.20.dist-info/WHEEL
projectowl-0.3.20.dist-info/top_level.txt
projectowl-0.3.20.dist-info/RECORD
