Metadata-Version: 2.1
Name: projectowl
Version: 0.3.20
Summary: Utility library for building python app
Home-page: https://github.com/flyfj/projectowl.git
Author: Jie Feng
Author-email: jiefeng@perceptance.io
License: UNKNOWN
Platform: UNKNOWN
Classifier: Programming Language :: Python :: 3
Classifier: License :: OSI Approved :: MIT License
Classifier: Operating System :: OS Independent
Requires-Dist: pymongo
Requires-Dist: boto3
Requires-Dist: tinyimage
Requires-Dist: dnspython
Requires-Dist: sendgrid (==6.0.4)
Requires-Dist: requests
Requires-Dist: python-http-client
Requires-Dist: jinja2
Requires-Dist: flask
Requires-Dist: tornado
Requires-Dist: flask-cors
